MANIFEST.in
README.md
menu.py
setup.py
src/directory.py
src/display.py
src/mariadb.py
src/openpanthera.egg-info/PKG-INFO
src/openpanthera.egg-info/SOURCES.txt
src/openpanthera.egg-info/dependency_links.txt
src/openpanthera.egg-info/requires.txt
src/openpanthera.egg-info/top_level.txt